setup.py
datastore/__init__.py
datastore.pylru.egg-info/PKG-INFO
datastore.pylru.egg-info/SOURCES.txt
datastore.pylru.egg-info/dependency_links.txt
datastore.pylru.egg-info/namespace_packages.txt
datastore.pylru.egg-info/requires.txt
datastore.pylru.egg-info/top_level.txt
datastore/pylru/__init__.py
datastore/pylru/test.py