Metadata-Version: 1.0
Name: datastore.pylru
Version: 0.1.1
Summary: pylru datastore implementation
Home-page: http://github.com/datastore/datastore.pylru
Author: Juan Batiz-Benet
Author-email: juan@benet.ai
License: MIT License
Keywords: datastore,pylru
Platform: UNKNOWN
Classifier: Topic :: Database
Classifier: Topic :: Database :: Front-Ends
